[
  {
    "match_id": 8555476710,
    "match_date": "2025-11-12 18:38 UTC",
    "radiant_team": "Zero Tenacity",
    "dire_team": "Most Wanted",
    "player_name": "nefrit",
    "items": [
      "Crimson Guard",
      "Power Treads",
      "Lotus Orb",
      "Black King Bar",
      "Magic Wand",
      "Platemail"
    ],
    "backpack": [
      "Unknown",
      "Unknown",
      "Unknown"
    ],
    "neutral_item": "Gale Guard",
    "win": false,
    "kda": {
      "kills": 2,
      "deaths": 3,
      "assists": 9
    },
    "item_timestamps": {
      "branches": 0,
      "circlet": 1,
      "magic_stick": 0,
      "gauntlets": 0,
      "tango": 0,
      "bracer": 0,
      "mantle": 1,
      "null_talisman": 1,
      "magic_wand": 2,
      "boots": 3,
      "ring_of_health": 21,
      "clarity": 29,
      "vitality_booster": 6,
      "vanguard": 6,
      "belt_of_strength": 8,
      "gloves": 8,
      "power_treads": 9,
      "helm_of_iron_will": 10,
      "tpscroll": 29,
      "crimson_guard": 13,
      "aghanims_shard": 16,
      "void_stone": 17,
      "pers": 21,
      "platemail": 32,
      "energy_booster": 23,
      "lotus_orb": 24,
      "ogre_axe": 27,
      "mithril_hammer": 27,
      "black_king_bar": 28,
      "enchanted_mango": 35
    },
    "bought_aghs": false,
    "bought_shard": true
  },
  {
    "match_id": 8555271773,
    "match_date": "2025-11-12 16:19 UTC",
    "radiant_team": "LSG",
    "dire_team": "Dark Rebellion",
    "player_name": "Vahee",
    "items": [
      "Magic Wand",
      "Power Treads",
      "Lotus Orb",
      "Sange And Yasha",
      "Helm Of Iron Will",
      "Branches"
    ],
    "backpack": [
      "Unknown",
      "Unknown",
      "Unknown"
    ],
    "neutral_item": "Essence Ring",
    "win": true,
    "kda": {
      "kills": 9,
      "deaths": 3,
      "assists": 5
    },
    "item_timestamps": {
      "magic_stick": 0,
      "branches": 0,
      "magic_wand": 0,
      "boots": 2,
      "gloves": 2,
      "power_treads": 3,
      "belt_of_strength": 10,
      "ring_of_health": 5,
      "void_stone": 6,
      "pers": 6,
      "platemail": 8,
      "lotus_orb": 9,
      "energy_booster": 9,
      "ogre_axe": 12,
      "blade_of_alacrity": 15,
      "sange": 15,
      "boots_of_elves": 16,
      "yasha": 17,
      "sange_and_yasha": 17,
      "helm_of_iron_will": 18,
      "relic": 22
    },
    "bought_aghs": false,
    "bought_shard": false
  },
  {
    "match_id": 8555241438,
    "match_date": "2025-11-12 16:02 UTC",
    "radiant_team": "52TURBO",
    "dire_team": "Devils in Hats",
    "player_name": "ness",
    "items": [
      "Sange And Yasha",
      "Ultimate Scepter",
      "Bracer",
      "Pers",
      "Power Treads",
      "Heart"
    ],
    "backpack": [
      "Unknown",
      "Unknown",
      "Unknown"
    ],
    "neutral_item": "Pogo Stick",
    "win": true,
    "kda": {
      "kills": 18,
      "deaths": 1,
      "assists": 9
    },
    "item_timestamps": {
      "magic_wand": 0,
      "branches": 0,
      "tango": 0,
      "circlet": 1,
      "gauntlets": 2,
      "bracer": 3,
      "mantle": 3,
      "belt_of_strength": 11,
      "null_talisman": 4,
      "boots": 5,
      "infused_raindrop": 5,
      "gloves": 6,
      "clarity": 6,
      "power_treads": 7,
      "ring_of_health": 8,
      "void_stone": 8,
      "pers": 9,
      "ogre_axe": 24,
      "sange": 12,
      "blade_of_alacrity": 24,
      "boots_of_elves": 14,
      "yasha": 14,
      "sange_and_yasha": 14,
      "reaver": 16,
      "ring_of_tarrasque": 20,
      "heart": 20,
      "aghanims_shard": 21,
      "staff_of_wizardry": 24,
      "ultimate_scepter": 25,
      "point_booster": 25
    },
    "bought_aghs": false,
    "bought_shard": true
  },
  {
    "match_id": 8555021428,
    "match_date": "2025-11-12 14:01 UTC",
    "radiant_team": "LV United",
    "dire_team": "Night Force",
    "player_name": "timothydillon1990",
    "items": [
      "Power Treads",
      "Crimson Guard",
      "Magic Wand",
      "Null Talisman",
      "Ring Of Tarrasque",
      "Null Talisman"
    ],
    "backpack": [
      "Cloak",
      "Unknown",
      "Ring Of Regen"
    ],
    "neutral_item": "Misericorde",
    "win": false,
    "kda": {
      "kills": 8,
      "deaths": 7,
      "assists": 0
    },
    "item_timestamps": {
      "tango": 0,
      "branches": 0,
      "magic_stick": 0,
      "circlet": 12,
      "gauntlets": 1,
      "bracer": 1,
      "mantle": 12,
      "gloves": 4,
      "belt_of_strength": 4,
      "power_treads": 5,
      "boots": 5,
      "null_talisman": 13,
      "magic_wand": 6,
      "vitality_booster": 7,
      "vanguard": 8,
      "ring_of_health": 8,
      "blood_grenade": 8,
      "helm_of_iron_will": 9,
      "crimson_guard": 11,
      "cloak": 17,
      "ring_of_tarrasque": 16,
      "ring_of_regen": 18
    },
    "bought_aghs": false,
    "bought_shard": false
  },
  {
    "match_id": 8555010513,
    "match_date": "2025-11-12 13:54 UTC",
    "radiant_team": "Zero Tenacity",
    "dire_team": "NAVI Junior",
    "player_name": "nefrit",
    "items": [
      "Pipe",
      "Power Treads",
      "Assault",
      "Black King Bar",
      "Magic Wand",
      "Null Talisman"
    ],
    "backpack": [
      "Unknown",
      "Unknown",
      "Unknown"
    ],
    "neutral_item": "Gale Guard",
    "win": true,
    "kda": {
      "kills": 7,
      "deaths": 1,
      "assists": 16
    },
    "item_timestamps": {
      "circlet": 2,
      "branches": 0,
      "magic_stick": 0,
      "gauntlets": 0,
      "tango": 2,
      "mantle": 1,
      "bracer": 1,
      "null_talisman": 4,
      "magic_wand": 4,
      "flask": 4,
      "belt_of_strength": 5,
      "boots": 6,
      "gloves": 8,
      "power_treads": 8,
      "ring_of_tarrasque": 11,
      "clarity": 30,
      "cloak": 12,
      "ring_of_regen": 14,
      "headdress": 14,
      "pipe": 14,
      "aghanims_shard": 16,
      "ogre_axe": 17,
      "mithril_hammer": 19,
      "tpscroll": 29,
      "black_king_bar": 21,
      "platemail": 24,
      "ring_of_protection": 27,
      "buckler": 27,
      "hyperstone": 29,
      "assault": 29
    },
    "bought_aghs": false,
    "bought_shard": true
  }
]