[
  {
    "match_id": 8283297432,
    "match_date": "2025-05-06 22:55 UTC",
    "radiant_team": "VERTEX PACK",
    "dire_team": "Silent killer",
    "player_name": "sK.itras",
    "items": [
      "Guardian Greaves",
      "Heavens Halberd",
      "Magic Wand",
      "Quelling Blade",
      "Bracer",
      "Blade Mail"
    ],
    "backpack": [
      "Unknown",
      "Unknown",
      "Unknown"
    ],
    "neutral_item": "Iron Talon",
    "win": false,
    "kda": {
      "kills": 4,
      "deaths": 7,
      "assists": 5
    },
    "item_timestamps": {
      "quelling_blade": 0,
      "tango": 3,
      "circlet": 0,
      "faerie_fire": 0,
      "branches": 11,
      "gauntlets": 0,
      "ring_of_health": 2,
      "boots": 5,
      "vanguard": 9,
      "vitality_booster": 9,
      "bracer": 10,
      "magic_stick": 11,
      "magic_wand": 12,
      "sobi_mask": 13,
      "ring_of_basilius": 13,
      "arcane_boots": 13,
      "chainmail": 19,
      "tpscroll": 15,
      "broadsword": 16,
      "blade_mail": 17,
      "crown": 18,
      "heavens_halberd": 19,
      "ring_of_regen": 19,
      "headdress": 19,
      "ring_of_protection": 21,
      "mekansm": 20,
      "buckler": 21,
      "aghanims_shard": 23,
      "guardian_greaves": 29
    },
    "bought_aghs": false,
    "bought_shard": true
  },
  {
    "match_id": 8283068943,
    "match_date": "2025-05-06 18:11 UTC",
    "radiant_team": "Team Spirit",
    "dire_team": "PARIVISION",
    "player_name": "DM",
    "items": [
      "Heavens Halberd",
      "Magic Wand",
      "Black King Bar",
      "Pipe",
      "Power Treads",
      "Assault"
    ],
    "backpack": [
      "Unknown",
      "Unknown",
      "Unknown"
    ],
    "neutral_item": "Ogre Seal Totem",
    "win": true,
    "kda": {
      "kills": 6,
      "deaths": 4,
      "assists": 16
    },
    "item_timestamps": {
      "magic_stick": 0,
      "circlet": 0,
      "branches": 0,
      "tango": 0,
      "ring_of_health": 3,
      "vitality_booster": 6,
      "vanguard": 6,
      "clarity": 24,
      "boots": 7,
      "tpscroll": 24,
      "magic_wand": 8,
      "ring_of_protection": 36,
      "gauntlets": 8,
      "soul_ring": 10,
      "crown": 10,
      "heavens_halberd": 11,
      "cloak": 12,
      "dust": 22,
      "ring_of_tarrasque": 16,
      "ring_of_regen": 17,
      "headdress": 17,
      "pipe": 17,
      "aghanims_shard": 20,
      "belt_of_strength": 21,
      "gloves": 22,
      "power_treads": 22,
      "ogre_axe": 26,
      "mithril_hammer": 28,
      "black_king_bar": 28,
      "platemail": 34,
      "hyperstone": 35,
      "buckler": 36,
      "assault": 36
    },
    "bought_aghs": false,
    "bought_shard": true
  },
  {
    "match_id": 8283033420,
    "match_date": "2025-05-06 17:40 UTC",
    "radiant_team": null,
    "dire_team": "Purple rush",
    "player_name": "Odi",
    "items": [
      "Power Treads",
      "Blade Mail",
      "Sange And Yasha",
      "Null Talisman",
      "Vanguard",
      "Bracer"
    ],
    "backpack": [
      "Unknown",
      "Unknown",
      "Unknown"
    ],
    "neutral_item": "Essence Ring",
    "win": true,
    "kda": {
      "kills": 9,
      "deaths": 1,
      "assists": 30
    },
    "item_timestamps": {
      "circlet": 0,
      "tango": 0,
      "branches": 0,
      "enchanted_mango": 0,
      "mantle": 1,
      "null_talisman": 1,
      "gauntlets": 2,
      "magic_stick": 2,
      "bracer": 3,
      "magic_wand": 3,
      "boots": 4,
      "flask": 5,
      "belt_of_strength": 21,
      "gloves": 7,
      "power_treads": 8,
      "ring_of_health": 27,
      "vanguard": 10,
      "vitality_booster": 10,
      "broadsword": 12,
      "clarity": 16,
      "aghanims_shard": 16,
      "chainmail": 16,
      "blade_mail": 17,
      "tpscroll": 22,
      "ogre_axe": 19,
      "sange": 21,
      "blade_of_alacrity": 24,
      "boots_of_elves": 24,
      "yasha": 24,
      "sange_and_yasha": 24,
      "pers": 27,
      "void_stone": 27,
      "energy_booster": 27
    },
    "bought_aghs": false,
    "bought_shard": true
  },
  {
    "match_id": 8282909694,
    "match_date": "2025-05-06 15:56 UTC",
    "radiant_team": "PARIVISION",
    "dire_team": "Gaimin Gladiators",
    "player_name": "Ace \u2660",
    "items": [
      "Blade Mail",
      "Lotus Orb",
      "Power Treads",
      "Heart",
      "Vanguard",
      "Sange And Yasha"
    ],
    "backpack": [
      "Unknown",
      "Unknown",
      "Unknown"
    ],
    "neutral_item": "Pyrrhic Cloak",
    "win": true,
    "kda": {
      "kills": 1,
      "deaths": 6,
      "assists": 11
    },
    "item_timestamps": {
      "magic_wand": 0,
      "branches": 0,
      "tango": 2,
      "flask": 1,
      "ring_of_health": 32,
      "vitality_booster": 8,
      "vanguard": 8,
      "clarity": 10,
      "ring_of_protection": 11,
      "gauntlets": 11,
      "soul_ring": 11,
      "boots": 12,
      "gloves": 13,
      "belt_of_strength": 25,
      "power_treads": 14,
      "tpscroll": 20,
      "aghanims_shard": 16,
      "broadsword": 20,
      "chainmail": 20,
      "blade_mail": 20,
      "ogre_axe": 25,
      "sange": 25,
      "blade_of_alacrity": 27,
      "boots_of_elves": 27,
      "yasha": 27,
      "sange_and_yasha": 27,
      "platemail": 29,
      "pers": 32,
      "void_stone": 32,
      "energy_booster": 34,
      "lotus_orb": 34,
      "reaver": 39,
      "ring_of_tarrasque": 41,
      "heart": 41
    },
    "bought_aghs": false,
    "bought_shard": true
  },
  {
    "match_id": 8282653512,
    "match_date": "2025-05-06 12:42 UTC",
    "radiant_team": "Foxy gaming",
    "dire_team": null,
    "player_name": "Unknown",
    "items": [
      "Black King Bar",
      "Soul Ring",
      "Magic Wand",
      "Sange And Yasha",
      "Power Treads",
      "Heavens Halberd"
    ],
    "backpack": [
      "Quelling Blade",
      "Unknown",
      "Unknown"
    ],
    "neutral_item": "Essence Ring",
    "win": true,
    "kda": {
      "kills": 11,
      "deaths": 4,
      "assists": 16
    },
    "item_timestamps": {
      "quelling_blade": 0,
      "gauntlets": 11,
      "tango": 0,
      "branches": 0,
      "circlet": 0,
      "ring_of_health": 2,
      "magic_stick": 5,
      "magic_wand": 5,
      "vitality_booster": 7,
      "vanguard": 7,
      "boots": 8,
      "gloves": 8,
      "belt_of_strength": 16,
      "power_treads": 10,
      "ring_of_protection": 11,
      "soul_ring": 11,
      "blade_of_alacrity": 13,
      "boots_of_elves": 13,
      "tpscroll": 28,
      "yasha": 15,
      "ogre_axe": 21,
      "sange": 18,
      "sange_and_yasha": 19,
      "aghanims_shard": 20,
      "mithril_hammer": 24,
      "black_king_bar": 26,
      "crown": 28,
      "heavens_halberd": 28
    },
    "bought_aghs": false,
    "bought_shard": true
  }
]