[
  {
    "match_id": 8293504671,
    "match_date": "2025-05-14 22:13 UTC",
    "radiant_team": "Night Vision",
    "dire_team": "Silent killer",
    "player_name": "sK.itras",
    "items": [
      "Lotus Orb",
      "Soul Ring",
      "Heavens Halberd",
      "Reaver",
      "Power Treads",
      "Sange And Yasha"
    ],
    "backpack": [
      "Unknown",
      "Unknown",
      "Unknown"
    ],
    "neutral_item": "Whisper Of The Dread",
    "win": false,
    "kda": {
      "kills": 4,
      "deaths": 5,
      "assists": 4
    },
    "item_timestamps": {
      "tango": 0,
      "branches": 0,
      "gauntlets": 6,
      "magic_stick": 0,
      "ring_of_health": 22,
      "boots": 4,
      "vanguard": 5,
      "vitality_booster": 5,
      "ring_of_protection": 6,
      "soul_ring": 7,
      "magic_wand": 8,
      "belt_of_strength": 16,
      "gloves": 9,
      "power_treads": 9,
      "crown": 10,
      "heavens_halberd": 11,
      "aghanims_shard": 15,
      "ogre_axe": 15,
      "sange": 17,
      "tpscroll": 22,
      "boots_of_elves": 17,
      "blade_of_alacrity": 19,
      "yasha": 21,
      "sange_and_yasha": 21,
      "void_stone": 22,
      "pers": 22,
      "platemail": 26,
      "energy_booster": 27,
      "lotus_orb": 27,
      "reaver": 33
    },
    "bought_aghs": false,
    "bought_shard": true
  },
  {
    "match_id": 8293478405,
    "match_date": "2025-05-14 21:30 UTC",
    "radiant_team": "Wild Dragon",
    "dire_team": "TOXIC TEAM",
    "player_name": "Tt.Wired",
    "items": [
      "Heart",
      "Heavens Halberd",
      "Black King Bar",
      "Soul Ring",
      "Sange And Yasha",
      "Power Treads"
    ],
    "backpack": [
      "Unknown",
      "Unknown",
      "Unknown"
    ],
    "neutral_item": "Whisper Of The Dread",
    "win": true,
    "kda": {
      "kills": 5,
      "deaths": 4,
      "assists": 10
    },
    "item_timestamps": {
      "tango": 0,
      "magic_stick": 0,
      "branches": 0,
      "gauntlets": 7,
      "ring_of_health": 2,
      "boots": 3,
      "magic_wand": 5,
      "vitality_booster": 6,
      "vanguard": 6,
      "ring_of_protection": 7,
      "soul_ring": 8,
      "gloves": 9,
      "belt_of_strength": 19,
      "power_treads": 10,
      "aghanims_shard": 15,
      "crown": 15,
      "heavens_halberd": 15,
      "ogre_axe": 22,
      "sange": 19,
      "blade_of_alacrity": 21,
      "boots_of_elves": 21,
      "yasha": 21,
      "sange_and_yasha": 21,
      "mithril_hammer": 24,
      "black_king_bar": 25,
      "reaver": 28,
      "tpscroll": 29,
      "ring_of_tarrasque": 31,
      "heart": 31
    },
    "bought_aghs": false,
    "bought_shard": true
  },
  {
    "match_id": 8293352062,
    "match_date": "2025-05-14 19:14 UTC",
    "radiant_team": "MOUZ",
    "dire_team": "Edge",
    "player_name": "zeal",
    "items": [
      "Crimson Guard",
      "Ghost",
      "Magic Wand",
      "Dust",
      "Soul Ring",
      "Power Treads"
    ],
    "backpack": [
      "Clarity",
      "Unknown",
      "Unknown"
    ],
    "neutral_item": "Gossamer Cape",
    "win": false,
    "kda": {
      "kills": 0,
      "deaths": 11,
      "assists": 4
    },
    "item_timestamps": {
      "tango": 0,
      "faerie_fire": 0,
      "magic_stick": 0,
      "enchanted_mango": 0,
      "ring_of_protection": 0,
      "boots": 2,
      "ring_of_health": 4,
      "vitality_booster": 8,
      "vanguard": 8,
      "gauntlets": 9,
      "soul_ring": 10,
      "gloves": 11,
      "belt_of_strength": 12,
      "clarity": 22,
      "power_treads": 13,
      "helm_of_iron_will": 14,
      "crimson_guard": 16,
      "aghanims_shard": 18,
      "branches": 18,
      "magic_wand": 19,
      "ghost": 22,
      "tpscroll": 22,
      "dust": 24
    },
    "bought_aghs": false,
    "bought_shard": true
  },
  {
    "match_id": 8293099336,
    "match_date": "2025-05-14 15:48 UTC",
    "radiant_team": "Wildcard",
    "dire_team": "AVULUS",
    "player_name": "\u043f\u043e\u043c\u043e\u0439\u043a\u0430",
    "items": [
      "Pipe",
      "Lotus Orb",
      "Basher",
      "Soul Ring",
      "Power Treads",
      "Sange"
    ],
    "backpack": [
      "Famango",
      "Dust",
      "Unknown"
    ],
    "neutral_item": "Gale Guard",
    "win": true,
    "kda": {
      "kills": 2,
      "deaths": 4,
      "assists": 19
    },
    "item_timestamps": {
      "gauntlets": 2,
      "tango": 5,
      "circlet": 0,
      "quelling_blade": 0,
      "branches": 0,
      "flask": 1,
      "bracer": 1,
      "magic_stick": 3,
      "magic_wand": 4,
      "boots": 5,
      "belt_of_strength": 37,
      "clarity": 7,
      "gloves": 8,
      "power_treads": 9,
      "ring_of_protection": 9,
      "soul_ring": 9,
      "cloak": 11,
      "aghanims_shard": 16,
      "ring_of_regen": 18,
      "headdress": 18,
      "ring_of_tarrasque": 20,
      "pipe": 20,
      "dust": 37,
      "ring_of_health": 25,
      "pers": 25,
      "void_stone": 25,
      "platemail": 28,
      "energy_booster": 28,
      "lotus_orb": 29,
      "ogre_axe": 35,
      "sange": 35,
      "mithril_hammer": 37,
      "basher": 37
    },
    "bought_aghs": false,
    "bought_shard": true
  },
  {
    "match_id": 8293018144,
    "match_date": "2025-05-14 14:44 UTC",
    "radiant_team": null,
    "dire_team": null,
    "player_name": "\u6bdb\u6bdb",
    "items": [
      "Power Treads",
      "Null Talisman",
      "Sange And Yasha",
      "Vanguard",
      "Bracer",
      "Blade Mail"
    ],
    "backpack": [
      "Unknown",
      "Unknown",
      "Unknown"
    ],
    "neutral_item": "Essence Ring",
    "win": true,
    "kda": {
      "kills": 4,
      "deaths": 6,
      "assists": 22
    },
    "item_timestamps": {
      "quelling_blade": 0,
      "tango": 2,
      "branches": 0,
      "gauntlets": 0,
      "enchanted_mango": 0,
      "circlet": 2,
      "bracer": 1,
      "mantle": 2,
      "null_talisman": 2,
      "flask": 3,
      "ring_of_health": 5,
      "magic_stick": 6,
      "magic_wand": 6,
      "vanguard": 10,
      "vitality_booster": 10,
      "boots": 11,
      "gloves": 12,
      "belt_of_strength": 21,
      "power_treads": 12,
      "broadsword": 14,
      "chainmail": 16,
      "blade_mail": 17,
      "ogre_axe": 21,
      "sange": 21,
      "aghanims_shard": 23,
      "blade_of_alacrity": 26,
      "boots_of_elves": 26,
      "yasha": 26,
      "sange_and_yasha": 26
    },
    "bought_aghs": false,
    "bought_shard": true
  }
]