[
  {
    "match_id": 8605594464,
    "match_date": "2025-12-14 20:08 UTC",
    "radiant_team": "HolyTeam",
    "dire_team": "Moonwalkers",
    "player_name": "HT.Nagama",
    "items": [
      "Pipe",
      "Power Treads",
      "Blade Mail",
      "Lotus Orb",
      "Magic Wand",
      "Helm Of Iron Will"
    ],
    "backpack": [
      "Ring Of Health",
      "Unknown",
      "Unknown"
    ],
    "neutral_item": "Chipped Vest",
    "win": true,
    "kda": {
      "kills": 7,
      "deaths": 5,
      "assists": 16
    },
    "item_timestamps": {
      "branches": 0,
      "quelling_blade": 0,
      "tango": 0,
      "circlet": 1,
      "gauntlets": 0,
      "bracer": 0,
      "mantle": 2,
      "null_talisman": 3,
      "magic_stick": 3,
      "wind_lace": 3,
      "enchanted_mango": 3,
      "magic_wand": 4,
      "boots": 5,
      "gloves": 6,
      "belt_of_strength": 7,
      "flask": 7,
      "power_treads": 8,
      "chainmail": 8,
      "broadsword": 10,
      "blade_mail": 12,
      "platemail": 14,
      "tpscroll": 20,
      "ring_of_health": 29,
      "pers": 16,
      "void_stone": 16,
      "energy_booster": 18,
      "lotus_orb": 18,
      "aghanims_shard": 20,
      "ring_of_tarrasque": 24,
      "ring_of_regen": 24,
      "headdress": 24,
      "pipe": 25,
      "cloak": 25,
      "helm_of_iron_will": 27
    },
    "bought_aghs": false,
    "bought_shard": true
  },
  {
    "match_id": 8605410575,
    "match_date": "2025-12-14 17:46 UTC",
    "radiant_team": "\u0431\u0430\u0440\u0441\u0435\u043b\u043e\u043d\u0430",
    "dire_team": "\u0420\u044f\u0437\u0430\u043d\u044c-\u0412\u0414\u0412",
    "player_name": "Sky-Rzn",
    "items": [
      "Blade Mail",
      "Black King Bar",
      "Sphere",
      "Magic Wand",
      "Assault",
      "Power Treads"
    ],
    "backpack": [
      "Unknown",
      "Unknown",
      "Unknown"
    ],
    "neutral_item": "Gunpowder Gauntlets",
    "win": true,
    "kda": {
      "kills": 8,
      "deaths": 5,
      "assists": 8
    },
    "item_timestamps": {
      "tango": 0,
      "branches": 0,
      "circlet": 3,
      "magic_stick": 0,
      "enchanted_mango": 0,
      "gauntlets": 1,
      "bracer": 2,
      "mantle": 3,
      "null_talisman": 3,
      "boots": 4,
      "flask": 5,
      "belt_of_strength": 5,
      "magic_wand": 5,
      "gloves": 6,
      "power_treads": 7,
      "chainmail": 7,
      "broadsword": 8,
      "blade_mail": 10,
      "void_stone": 10,
      "ring_of_health": 12,
      "tpscroll": 12,
      "pers": 12,
      "aghanims_shard": 15,
      "mithril_hammer": 18,
      "ogre_axe": 18,
      "black_king_bar": 19,
      "ultimate_orb": 24,
      "sphere": 24,
      "platemail": 26,
      "hyperstone": 28,
      "ring_of_protection": 28,
      "buckler": 28,
      "assault": 29
    },
    "bought_aghs": false,
    "bought_shard": true
  },
  {
    "match_id": 8605272649,
    "match_date": "2025-12-14 16:12 UTC",
    "radiant_team": "Eye Gaming",
    "dire_team": "La Passion",
    "player_name": "PVE tower defense",
    "items": [
      "Sange And Yasha",
      "Lotus Orb",
      "Power Treads",
      "Magic Wand",
      "Blade Mail",
      "Null Talisman"
    ],
    "backpack": [
      "Unknown",
      "Unknown",
      "Unknown"
    ],
    "neutral_item": "Poor Mans Shield",
    "win": true,
    "kda": {
      "kills": 1,
      "deaths": 4,
      "assists": 10
    },
    "item_timestamps": {
      "circlet": 0,
      "gauntlets": 0,
      "branches": 0,
      "tango": 3,
      "bracer": 0,
      "mantle": 1,
      "null_talisman": 2,
      "magic_stick": 2,
      "magic_wand": 2,
      "boots": 4,
      "gloves": 6,
      "belt_of_strength": 25,
      "power_treads": 8,
      "tpscroll": 24,
      "broadsword": 10,
      "chainmail": 11,
      "blade_mail": 12,
      "ring_of_health": 13,
      "pers": 14,
      "void_stone": 14,
      "clarity": 14,
      "platemail": 18,
      "energy_booster": 18,
      "lotus_orb": 19,
      "blade_of_alacrity": 21,
      "boots_of_elves": 21,
      "yasha": 23,
      "ogre_axe": 25,
      "sange": 27,
      "sange_and_yasha": 27
    },
    "bought_aghs": false,
    "bought_shard": false
  },
  {
    "match_id": 8605157017,
    "match_date": "2025-12-14 15:02 UTC",
    "radiant_team": "Swashbuckle",
    "dire_team": "point g",
    "player_name": "\u042f\u0438\u0447\u043a\u0438\u0412\u0422\u0440\u0435\u0445\u043c\u0435\u0440\u043d\u043e\u0439",
    "items": [
      "Power Treads",
      "Lotus Orb",
      "Abyssal Blade",
      "Heavens Halberd",
      "Blade Mail",
      "Sange And Yasha"
    ],
    "backpack": [
      "Unknown",
      "Roshans Banner",
      "Unknown"
    ],
    "neutral_item": "Whisper Of The Dread",
    "win": true,
    "kda": {
      "kills": 13,
      "deaths": 10,
      "assists": 13
    },
    "item_timestamps": {
      "branches": 1,
      "tango": 0,
      "gauntlets": 3,
      "circlet": 0,
      "magic_stick": 1,
      "bracer": 4,
      "clarity": 2,
      "enchanted_mango": 20,
      "magic_wand": 3,
      "boots": 5,
      "gloves": 5,
      "power_treads": 6,
      "belt_of_strength": 39,
      "chainmail": 7,
      "broadsword": 8,
      "blade_mail": 10,
      "ogre_axe": 37,
      "sange": 41,
      "boots_of_elves": 13,
      "blade_of_alacrity": 15,
      "tpscroll": 38,
      "yasha": 17,
      "sange_and_yasha": 17,
      "aghanims_shard": 19,
      "ring_of_health": 28,
      "vanguard": 23,
      "vitality_booster": 23,
      "crown": 25,
      "heavens_halberd": 28,
      "pers": 28,
      "void_stone": 28,
      "platemail": 30,
      "energy_booster": 30,
      "lotus_orb": 30,
      "mithril_hammer": 35,
      "basher": 36,
      "abyssal_blade": 48
    },
    "bought_aghs": false,
    "bought_shard": true
  },
  {
    "match_id": 8605007962,
    "match_date": "2025-12-14 13:38 UTC",
    "radiant_team": "Swashbuckle",
    "dire_team": "SMOKE AND FEED",
    "player_name": "\u0426\u044b\u0433\u0430",
    "items": [
      "Magic Wand",
      "Quelling Blade",
      "Power Treads",
      "Vanguard",
      "Bracer",
      "Unknown"
    ],
    "backpack": [
      "Unknown",
      "Unknown",
      "Unknown"
    ],
    "neutral_item": "Chipped Vest",
    "win": false,
    "kda": {
      "kills": 2,
      "deaths": 2,
      "assists": 1
    },
    "item_timestamps": {
      "branches": 0,
      "faerie_fire": 0,
      "magic_stick": 0,
      "circlet": 0,
      "tango": 0,
      "quelling_blade": 0,
      "gauntlets": 2,
      "bracer": 3,
      "magic_wand": 3,
      "flask": 4,
      "ring_of_health": 6,
      "vitality_booster": 7,
      "vanguard": 8,
      "boots": 8,
      "gloves": 11,
      "belt_of_strength": 11,
      "power_treads": 11,
      "clarity": 12
    },
    "bought_aghs": false,
    "bought_shard": false
  }
]