[
  {
    "match_id": 8288121305,
    "match_date": "2025-05-10 17:30 UTC",
    "radiant_team": "Yagodki Prime",
    "dire_team": "5DOGS",
    "player_name": "\u0418\u043e\u0441\u0438\u0444 \u0421\u0442\u0430\u043d\u0438\u043d",
    "items": [
      "Heavens Halberd",
      "Pipe",
      "Abyssal Blade",
      "Power Treads",
      "Null Talisman",
      "Sange And Yasha"
    ],
    "backpack": [
      "Unknown",
      "Unknown",
      "Dust"
    ],
    "neutral_item": "Gale Guard",
    "win": true,
    "kda": {
      "kills": 14,
      "deaths": 6,
      "assists": 23
    },
    "item_timestamps": {
      "quelling_blade": 0,
      "branches": 0,
      "tango": 0,
      "circlet": 0,
      "magic_stick": 0,
      "mantle": 0,
      "null_talisman": 0,
      "ring_of_health": 3,
      "vitality_booster": 6,
      "vanguard": 6,
      "infused_raindrop": 11,
      "boots": 8,
      "gloves": 9,
      "belt_of_strength": 34,
      "power_treads": 10,
      "tpscroll": 16,
      "ogre_axe": 34,
      "sange": 34,
      "blade_of_alacrity": 18,
      "boots_of_elves": 18,
      "yasha": 18,
      "sange_and_yasha": 19,
      "ring_of_tarrasque": 20,
      "cloak": 24,
      "ring_of_regen": 24,
      "headdress": 24,
      "pipe": 24,
      "dust": 26,
      "crown": 27,
      "heavens_halberd": 27,
      "aghanims_shard": 28,
      "mithril_hammer": 32,
      "basher": 32,
      "abyssal_blade": 35
    },
    "bought_aghs": false,
    "bought_shard": true
  },
  {
    "match_id": 8287834596,
    "match_date": "2025-05-10 14:18 UTC",
    "radiant_team": null,
    "dire_team": "\u0425\u0415\u0419\u0422\u0415\u0420\u042b \u0414\u0415\u041d\u0410",
    "player_name": "Paliamola",
    "items": [
      "Power Treads",
      "Bracer",
      "Quelling Blade",
      "Heavens Halberd",
      "Magic Stick",
      "Bracer"
    ],
    "backpack": [
      "Unknown",
      "Unknown",
      "Unknown"
    ],
    "neutral_item": "Polliwog Charm",
    "win": false,
    "kda": {
      "kills": 4,
      "deaths": 7,
      "assists": 3
    },
    "item_timestamps": {
      "gauntlets": 0,
      "circlet": 0,
      "tango": 4,
      "quelling_blade": 0,
      "bracer": 2,
      "boots": 3,
      "magic_stick": 4,
      "ring_of_health": 5,
      "vitality_booster": 7,
      "vanguard": 8,
      "gloves": 9,
      "belt_of_strength": 10,
      "power_treads": 10,
      "crown": 13,
      "heavens_halberd": 13,
      "aghanims_shard": 16
    },
    "bought_aghs": false,
    "bought_shard": true
  },
  {
    "match_id": 8287556253,
    "match_date": "2025-05-10 10:53 UTC",
    "radiant_team": "Teiko",
    "dire_team": "la passion",
    "player_name": "vogel",
    "items": [
      "Soul Ring",
      "Blade Mail",
      "Sange And Yasha",
      "Power Treads",
      "Lotus Orb",
      "Vitality Booster"
    ],
    "backpack": [
      "Unknown",
      "Unknown",
      "Roshans Banner"
    ],
    "neutral_item": "Gale Guard",
    "win": true,
    "kda": {
      "kills": 5,
      "deaths": 8,
      "assists": 15
    },
    "item_timestamps": {
      "gauntlets": 7,
      "tango": 0,
      "branches": 0,
      "magic_stick": 0,
      "boots": 2,
      "ring_of_health": 5,
      "vitality_booster": 6,
      "vanguard": 6,
      "ring_of_protection": 7,
      "soul_ring": 8,
      "magic_wand": 11,
      "chainmail": 11,
      "broadsword": 12,
      "tpscroll": 29,
      "blade_mail": 14,
      "aghanims_shard": 17,
      "dust": 21,
      "great_famango": 20,
      "gloves": 21,
      "power_treads": 21,
      "belt_of_strength": 25,
      "ogre_axe": 39,
      "sange": 25,
      "blade_of_alacrity": 28,
      "boots_of_elves": 28,
      "yasha": 28,
      "sange_and_yasha": 28,
      "void_stone": 36,
      "platemail": 36,
      "energy_booster": 36,
      "pers": 37,
      "lotus_orb": 37,
      "cloak": 39
    },
    "bought_aghs": false,
    "bought_shard": true
  },
  {
    "match_id": 8287535439,
    "match_date": "2025-05-10 10:34 UTC",
    "radiant_team": null,
    "dire_team": "Ghost Sheep",
    "player_name": "Keyleth",
    "items": [
      "Power Treads",
      "Soul Ring",
      "Black King Bar",
      "Ultimate Scepter",
      "Sange And Yasha",
      "Vanguard"
    ],
    "backpack": [
      "Unknown",
      "Unknown",
      "Unknown"
    ],
    "neutral_item": "Pogo Stick",
    "win": true,
    "kda": {
      "kills": 15,
      "deaths": 5,
      "assists": 14
    },
    "item_timestamps": {
      "tango": 0,
      "quelling_blade": 0,
      "magic_stick": 0,
      "faerie_fire": 0,
      "branches": 0,
      "enchanted_mango": 5,
      "ring_of_health": 1,
      "vitality_booster": 4,
      "vanguard": 4,
      "boots": 6,
      "ring_of_protection": 6,
      "gauntlets": 7,
      "magic_wand": 7,
      "soul_ring": 8,
      "gloves": 8,
      "belt_of_strength": 23,
      "power_treads": 10,
      "tpscroll": 30,
      "point_booster": 12,
      "ogre_axe": 29,
      "staff_of_wizardry": 15,
      "blade_of_alacrity": 25,
      "ultimate_scepter": 17,
      "aghanims_shard": 21,
      "sange": 23,
      "yasha": 25,
      "boots_of_elves": 25,
      "sange_and_yasha": 26,
      "mithril_hammer": 29,
      "black_king_bar": 29
    },
    "bought_aghs": false,
    "bought_shard": true
  },
  {
    "match_id": 8287476890,
    "match_date": "2025-05-10 09:36 UTC",
    "radiant_team": "Teiko",
    "dire_team": "la passion",
    "player_name": "vogel",
    "items": [
      "Branches",
      "Soul Ring",
      "Blade Mail",
      "Power Treads",
      "Bracer",
      "Magic Stick"
    ],
    "backpack": [
      "Branches",
      "Branches",
      "Unknown"
    ],
    "neutral_item": "Misericorde",
    "win": false,
    "kda": {
      "kills": 2,
      "deaths": 9,
      "assists": 1
    },
    "item_timestamps": {
      "tango": 0,
      "gauntlets": 9,
      "branches": 0,
      "magic_stick": 0,
      "boots": 2,
      "ring_of_protection": 5,
      "soul_ring": 5,
      "gloves": 8,
      "power_treads": 8,
      "belt_of_strength": 8,
      "circlet": 9,
      "bracer": 9,
      "tpscroll": 10,
      "broadsword": 15,
      "chainmail": 15,
      "blade_mail": 15,
      "aghanims_shard": 20
    },
    "bought_aghs": false,
    "bought_shard": true
  }
]