[
  {
    "match_id": 8647148151,
    "match_date": "2026-01-13 01:36 UTC",
    "radiant_team": "Chandogs",
    "dire_team": "Argentina",
    "player_name": "VOLANDO LLEGO",
    "items": [
      "Power Treads",
      "Black King Bar",
      "Blade Mail",
      "Lotus Orb",
      "Dust",
      "Sange And Yasha"
    ],
    "backpack": [
      "Unknown",
      "Unknown",
      "Unknown"
    ],
    "neutral_item": "Rattlecage",
    "win": false,
    "kda": {
      "kills": 8,
      "deaths": 8,
      "assists": 6
    },
    "item_timestamps": {
      "circlet": 0,
      "branches": 0,
      "enchanted_mango": 1,
      "tango": 3,
      "gauntlets": 0,
      "magic_stick": 1,
      "mantle": 2,
      "bracer": 3,
      "null_talisman": 3,
      "magic_wand": 3,
      "ward_sentry": 28,
      "boots": 4,
      "flask": 7,
      "ring_of_health": 5,
      "clarity": 19,
      "void_stone": 10,
      "belt_of_strength": 27,
      "gloves": 7,
      "tpscroll": 9,
      "power_treads": 9,
      "chainmail": 12,
      "pers": 11,
      "broadsword": 13,
      "blade_mail": 16,
      "aghanims_shard": 18,
      "platemail": 23,
      "energy_booster": 24,
      "lotus_orb": 24,
      "ogre_axe": 37,
      "sange": 28,
      "blade_of_alacrity": 30,
      "boots_of_elves": 31,
      "yasha": 31,
      "sange_and_yasha": 31,
      "mithril_hammer": 37,
      "black_king_bar": 37,
      "dust": 37
    },
    "bought_aghs": false,
    "bought_shard": true
  },
  {
    "match_id": 8647087531,
    "match_date": "2026-01-12 23:39 UTC",
    "radiant_team": null,
    "dire_team": null,
    "player_name": "VOLANDO LLEGO",
    "items": [
      "Power Treads",
      "Heart",
      "Blade Mail",
      "Black King Bar",
      "Assault",
      "Sange And Yasha"
    ],
    "backpack": [
      "Clarity",
      "Unknown",
      "Unknown"
    ],
    "neutral_item": "Crippling Crossbow",
    "win": true,
    "kda": {
      "kills": 10,
      "deaths": 7,
      "assists": 20
    },
    "item_timestamps": {
      "branches": 0,
      "magic_stick": 0,
      "enchanted_mango": 4,
      "gauntlets": 0,
      "tango": 4,
      "circlet": 5,
      "bracer": 2,
      "boots": 3,
      "magic_wand": 5,
      "mantle": 5,
      "flask": 6,
      "null_talisman": 6,
      "ring_of_health": 7,
      "tpscroll": 46,
      "ward_sentry": 8,
      "void_stone": 9,
      "pers": 10,
      "gloves": 10,
      "belt_of_strength": 17,
      "power_treads": 11,
      "chainmail": 11,
      "clarity": 44,
      "broadsword": 13,
      "blade_mail": 15,
      "aghanims_shard": 16,
      "ogre_axe": 24,
      "sange": 19,
      "blade_of_alacrity": 20,
      "boots_of_elves": 21,
      "yasha": 22,
      "sange_and_yasha": 22,
      "mithril_hammer": 26,
      "black_king_bar": 29,
      "reaver": 34,
      "ring_of_tarrasque": 36,
      "heart": 36,
      "hyperstone": 38,
      "greater_famango": 39,
      "buckler": 46,
      "ring_of_protection": 46,
      "platemail": 48,
      "assault": 48
    },
    "bought_aghs": false,
    "bought_shard": true
  },
  {
    "match_id": 8646641199,
    "match_date": "2026-01-12 15:54 UTC",
    "radiant_team": "Wiser Warriors",
    "dire_team": "Nova Pulse",
    "player_name": "NP.infinity",
    "items": [
      "Soul Ring",
      "Power Treads",
      "Sange And Yasha",
      "Vanguard",
      "Magic Wand",
      "Dust"
    ],
    "backpack": [
      "Unknown",
      "Unknown",
      "Unknown"
    ],
    "neutral_item": "Mana Draught",
    "win": false,
    "kda": {
      "kills": 4,
      "deaths": 5,
      "assists": 8
    },
    "item_timestamps": {
      "ring_of_protection": 0,
      "gauntlets": 0,
      "branches": 0,
      "tango": 0,
      "ring_of_health": 2,
      "magic_stick": 4,
      "magic_wand": 4,
      "vanguard": 6,
      "vitality_booster": 23,
      "boots": 7,
      "gloves": 8,
      "belt_of_strength": 13,
      "power_treads": 10,
      "soul_ring": 11,
      "ogre_axe": 13,
      "sange": 15,
      "blade_of_alacrity": 15,
      "boots_of_elves": 16,
      "yasha": 17,
      "sange_and_yasha": 17,
      "aghanims_shard": 18,
      "tpscroll": 19,
      "energy_booster": 23,
      "dust": 24,
      "soul_booster": 24,
      "point_booster": 24
    },
    "bought_aghs": false,
    "bought_shard": true
  },
  {
    "match_id": 8646576759,
    "match_date": "2026-01-12 15:07 UTC",
    "radiant_team": null,
    "dire_team": null,
    "player_name": "GAMBOT-PARIS",
    "items": [
      "Black King Bar",
      "Heart",
      "Mjollnir",
      "Swift Blink",
      "Abyssal Blade",
      "Sange And Yasha"
    ],
    "backpack": [
      "Great Famango",
      "Unknown",
      "Unknown"
    ],
    "neutral_item": "Flayers Bota",
    "win": false,
    "kda": {
      "kills": 18,
      "deaths": 7,
      "assists": 11
    },
    "item_timestamps": {
      "gauntlets": 0,
      "tango": 3,
      "branches": 5,
      "quelling_blade": 0,
      "magic_stick": 0,
      "circlet": 2,
      "bracer": 1,
      "mantle": 2,
      "null_talisman": 2,
      "boots": 4,
      "belt_of_strength": 36,
      "gloves": 50,
      "magic_wand": 7,
      "power_treads": 7,
      "broadsword": 8,
      "chainmail": 9,
      "blade_mail": 10,
      "ogre_axe": 36,
      "tpscroll": 32,
      "clarity": 45,
      "aghanims_shard": 15,
      "mithril_hammer": 50,
      "black_king_bar": 18,
      "sange": 36,
      "boots_of_elves": 21,
      "yasha": 22,
      "blade_of_alacrity": 22,
      "sange_and_yasha": 22,
      "reaver": 25,
      "heart": 31,
      "ring_of_tarrasque": 31,
      "basher": 36,
      "abyssal_blade": 36,
      "hyperstone": 50,
      "javelin": 50,
      "maelstrom": 50,
      "mjollnir": 50,
      "eagle": 54,
      "blink": 54,
      "swift_blink": 54
    },
    "bought_aghs": false,
    "bought_shard": true
  },
  {
    "match_id": 8646501064,
    "match_date": "2026-01-12 14:13 UTC",
    "radiant_team": "Inner Circle x Insanity",
    "dire_team": null,
    "player_name": "\u0444\u044b\u0432\u0430",
    "items": [
      "Power Treads",
      "Bracer",
      "Magic Wand",
      "Null Talisman",
      "Pipe",
      "Branches"
    ],
    "backpack": [
      "Unknown",
      "Unknown",
      "Unknown"
    ],
    "neutral_item": "Chipped Vest",
    "win": false,
    "kda": {
      "kills": 1,
      "deaths": 8,
      "assists": 2
    },
    "item_timestamps": {
      "circlet": 0,
      "tango": 4,
      "branches": 0,
      "gauntlets": 1,
      "bracer": 2,
      "mantle": 2,
      "null_talisman": 3,
      "magic_stick": 3,
      "flask": 3,
      "boots": 6,
      "magic_wand": 6,
      "belt_of_strength": 7,
      "ring_of_regen": 17,
      "power_treads": 9,
      "gloves": 9,
      "ring_of_tarrasque": 12,
      "cloak": 16,
      "headdress": 17,
      "pipe": 18,
      "aghanims_shard": 21
    },
    "bought_aghs": false,
    "bought_shard": true
  }
]